sitemessage/__init__.py
sitemessage/admin.py
sitemessage/apps.py
sitemessage/backends.py
sitemessage/exceptions.py
sitemessage/models.py
sitemessage/settings.py
sitemessage/shortcuts.py
sitemessage/signals.py
sitemessage/toolbox.py
sitemessage/utils.py
sitemessage/views.py
sitemessage/locale/en/LC_MESSAGES/django.po
sitemessage/locale/ru/LC_MESSAGES/django.mo
sitemessage/locale/ru/LC_MESSAGES/django.po
sitemessage/management/__init__.py
sitemessage/management/commands/__init__.py
sitemessage/management/commands/sitemessage_check_undelivered.py
sitemessage/management/commands/sitemessage_cleanup.py
sitemessage/management/commands/sitemessage_probe.py
sitemessage/management/commands/sitemessage_send_scheduled.py
sitemessage/messages/__init__.py
sitemessage/messages/base.py
sitemessage/messages/email.py
sitemessage/messages/plain.py
sitemessage/messengers/__init__.py
sitemessage/messengers/base.py
sitemessage/messengers/facebook.py
sitemessage/messengers/smtp.py
sitemessage/messengers/telegram.py
sitemessage/messengers/twitter.py
sitemessage/messengers/vkontakte.py
sitemessage/messengers/xmpp.py
sitemessage/migrations/0001_initial.py
sitemessage/migrations/0002_subscription.py
sitemessage/migrations/0003_auto_20210314_1053.py
sitemessage/migrations/0004_message_group_mark.py
sitemessage/migrations/__init__.py
sitemessage/static/img/sitemessage/blank.png
sitemessage/templates/sitemessage/user_prefs_table-bootstrap.html
sitemessage/templates/sitemessage/user_prefs_table.html
sitemessage/templates/sitemessage/messages/_base.html
sitemessage/templates/sitemessage/messages/email_html__smtp.html
sitemessage/templatetags/__init__.py
sitemessage/templatetags/sitemessage.py
django_sitemessage-1.4.0.dist-info/AUTHORS
django_sitemessage-1.4.0.dist-info/LICENSE
django_sitemessage-1.4.0.dist-info/METADATA
django_sitemessage-1.4.0.dist-info/WHEEL
django_sitemessage-1.4.0.dist-info/top_level.txt
django_sitemessage-1.4.0.dist-info/RECORD
